MANIFEST.in
README.rst
requirements.txt
setup.py
creh_urls_redirec.egg-info/PKG-INFO
creh_urls_redirec.egg-info/SOURCES.txt
creh_urls_redirec.egg-info/dependency_links.txt
creh_urls_redirec.egg-info/requires.txt
creh_urls_redirec.egg-info/top_level.txt
urls/__init__.py
urls/admin.py
urls/constants.py
urls/middleware.py
urls/models.py
urls/signals.py
urls/actions/__init__.py
urls/actions/register.py
urls/migrations/0001_initial.py
urls/migrations/0002_auto_20170509_1807.py
urls/migrations/0003_auto_20170509_1808.py
urls/migrations/0004_auto_20170515_2019.py
urls/migrations/__init__.py
urls/tests/__init__.py
urls/tests/test_actions.py
urls/tests/urls.py
urls/tests/views.py